mir/YMIR_VERSION
mir/__init__.py
mir/__main__.py
mir/cli.py
mir/main.py
mir/version.py
mir/commands/__init__.py
mir/commands/base.py
mir/commands/checkout.py
mir/commands/commit.py
mir/commands/copy.py
mir/commands/export.py
mir/commands/filter.py
mir/commands/fuse.py
mir/commands/import_dataset.py
mir/commands/import_model.py
mir/commands/infer.py
mir/commands/init.py
mir/commands/merge.py
mir/commands/mining.py
mir/commands/sampling.py
mir/commands/show.py
mir/commands/status.py
mir/commands/training.py
mir/protos/__init__.py
mir/protos/mir_command_pb2.py
mir/scm/__init__.py
mir/scm/base.py
mir/scm/cmd.py
mir/tools/__init__.py
mir/tools/annotations.py
mir/tools/checker.py
mir/tools/class_ids.py
mir/tools/code.py
mir/tools/command_run_in_out.py
mir/tools/env_config.py
mir/tools/errors.py
mir/tools/executant.py
mir/tools/exodus.py
mir/tools/exporter.py
mir/tools/metadatas.py
mir/tools/mir_repo_utils.py
mir/tools/mir_storage.py
mir/tools/mir_storage_ops.py
mir/tools/model_updater.py
mir/tools/models.py
mir/tools/percent_log_util.py
mir/tools/phase_logger.py
mir/tools/phase_logger_conf.json
mir/tools/revs_parser.py
mir/tools/settings.py
mir/tools/eval/__init__.py
mir/tools/eval/det_eval_voc.py
mir/tools/eval/eval_coco.py
mir/tools/eval/eval_ctl_ops.py
mir/tools/eval/eval_ops.py
mir/tools/eval/eval_utils.py
mir/tools/eval/ins_seg_eval_coco.py
mir/tools/eval/sem_seg_eval_mm.py
ymir_cmd-2.3.0.dist-info/LICENSE
ymir_cmd-2.3.0.dist-info/METADATA
ymir_cmd-2.3.0.dist-info/WHEEL
ymir_cmd-2.3.0.dist-info/entry_points.txt
ymir_cmd-2.3.0.dist-info/top_level.txt
ymir_cmd-2.3.0.dist-info/RECORD
