Metadata-Version: 2.1
Name: ymir-cmd
Version: 2.3.0
Summary: mir: A data version control tool for YMIR
Home-page: https://github.com/IndustryEssentials/ymir
Author-email: contact.viesc@gmail.com
Requires-Python: >=3.8.10
License-File: LICENSE
Requires-Dist: Pillow (==8.2.0)
Requires-Dist: fasteners (==0.16.3)
Requires-Dist: numpy (==1.22.0)
Requires-Dist: protobuf (==3.18.1)
Requires-Dist: pydantic (==1.9.0)
Requires-Dist: pyyaml (==5.4.1)
Requires-Dist: requests (==2.25.1)
Requires-Dist: retry (==0.9.2)
Requires-Dist: tensorboardX (==2.4.1)
Requires-Dist: xmltodict (==0.12.0)
